im_swagger_spy/__init__.py
im_swagger_spy/__main__.py
im_swagger_spy/base.py
im_swagger_spy/file_spy.py
im_swagger_spy/http_spy.py
im_swagger_spy/plugin.py
im_swagger_spy/syncdb.py
im_swagger_spy/template.html
im_swagger_spy/utils.py
im_swagger_spy-0.4.0.dist-info/METADATA
im_swagger_spy-0.4.0.dist-info/WHEEL
im_swagger_spy-0.4.0.dist-info/entry_points.txt
im_swagger_spy-0.4.0.dist-info/RECORD
