Metadata-Version: 2.1
Name: im-swagger-spy
Version: 0.4.0
Summary: im-swagger-spy: pytest plugin for matching methods in swagger with those used in tests
Project-URL: Homepage, https://github.com/dasshit/im-swagger-spy
Project-URL: Tracker, https://github.com/dasshit/im-swagger-spy/issues
Project-URL: Source, https://github.com/dasshit/im-swagger-spy
Author-email: Korobov Valerii <v.korobov@corp.mail.ru>
Keywords: plugin,pytest,pytest plugin,requests,swagger
Classifier: Development Status :: 5 - Production/Stable
Classifier: Framework :: Pytest
Classifier: Intended Audience :: Developers
Classifier: License :: OSI Approved :: MIT License
Classifier: Programming Language :: Python :: 3
Classifier: Programming Language :: Python :: 3 :: Only
Classifier: Programming Language :: Python :: 3.8
Classifier: Programming Language :: Python :: 3.9
Classifier: Programming Language :: Python :: 3.10
Classifier: Programming Language :: Python :: 3.11
Classifier: Programming Language :: Python :: 3.12
Classifier: Topic :: Software Development :: Quality Assurance
Classifier: Topic :: Software Development :: Testing
Requires-Python: >=3.8
Requires-Dist: jinja2>=3.0.0
Requires-Dist: peewee>=3.0.0
Requires-Dist: pytest>=7.0.0
Requires-Dist: pyyaml>=6.0
Requires-Dist: requests>=2.26.0
